WutongDeJiqiXuexiDierji/README.md
WutongDeJiqiXuexiDierji/__init__.py
WutongDeJiqiXuexiDierji/__main__.py
WutongDeJiqiXuexiDierji/file.epub
WutongDeJiqiXuexiDierji/index.html
WutongDeJiqiXuexiDierji/css/__init__.py
WutongDeJiqiXuexiDierji/css/annotations.css
WutongDeJiqiXuexiDierji/css/main.css
WutongDeJiqiXuexiDierji/css/normalize.css
WutongDeJiqiXuexiDierji/css/popup.css
WutongDeJiqiXuexiDierji/font/__init__.py
WutongDeJiqiXuexiDierji/font/fontello.eot
WutongDeJiqiXuexiDierji/font/fontello.svg
WutongDeJiqiXuexiDierji/font/fontello.ttf
WutongDeJiqiXuexiDierji/font/fontello.woff
WutongDeJiqiXuexiDierji/img/__init__.py
WutongDeJiqiXuexiDierji/img/annotator-glyph-sprite.png
WutongDeJiqiXuexiDierji/img/annotator-icon-sprite.png
WutongDeJiqiXuexiDierji/img/apple-touch-icon.png
WutongDeJiqiXuexiDierji/img/cancelfullscreen.png
WutongDeJiqiXuexiDierji/img/close.png
WutongDeJiqiXuexiDierji/img/fullscreen.png
WutongDeJiqiXuexiDierji/img/loader.gif
WutongDeJiqiXuexiDierji/img/menu-icon.png
WutongDeJiqiXuexiDierji/img/save.png
WutongDeJiqiXuexiDierji/img/saved.png
WutongDeJiqiXuexiDierji/img/settings-s.png
WutongDeJiqiXuexiDierji/img/settings.png
WutongDeJiqiXuexiDierji/img/star.png
WutongDeJiqiXuexiDierji/js/__init__.py
WutongDeJiqiXuexiDierji/js/epub.js
WutongDeJiqiXuexiDierji/js/epub.min.js
WutongDeJiqiXuexiDierji/js/epub.min.map
WutongDeJiqiXuexiDierji/js/hooks.min.js
WutongDeJiqiXuexiDierji/js/hooks.min.map
WutongDeJiqiXuexiDierji/js/reader.js
WutongDeJiqiXuexiDierji/js/reader.js.map
WutongDeJiqiXuexiDierji/js/reader.min.js
WutongDeJiqiXuexiDierji/js/reader.min.map
WutongDeJiqiXuexiDierji/js/hooks/__init__.py
WutongDeJiqiXuexiDierji/js/hooks/extensions/__init__.py
WutongDeJiqiXuexiDierji/js/hooks/extensions/highlight.js
WutongDeJiqiXuexiDierji/js/libs/__init__.py
WutongDeJiqiXuexiDierji/js/libs/jquery.min.js
WutongDeJiqiXuexiDierji/js/libs/localforage.min.js
WutongDeJiqiXuexiDierji/js/libs/screenfull.js
WutongDeJiqiXuexiDierji/js/libs/screenfull.min.js
wutong_de_jiqi_xuexi_dierji-2024.3.3.0.dist-info/METADATA
wutong_de_jiqi_xuexi_dierji-2024.3.3.0.dist-info/WHEEL
wutong_de_jiqi_xuexi_dierji-2024.3.3.0.dist-info/entry_points.txt
wutong_de_jiqi_xuexi_dierji-2024.3.3.0.dist-info/top_level.txt
wutong_de_jiqi_xuexi_dierji-2024.3.3.0.dist-info/RECORD
